odoo/addons/partner_category_description/README.rst
odoo/addons/partner_category_description/__init__.py
odoo/addons/partner_category_description/__manifest__.py
odoo/addons/partner_category_description/i18n/es.po
odoo/addons/partner_category_description/i18n/it.po
odoo/addons/partner_category_description/i18n/partner_category_description.pot
odoo/addons/partner_category_description/models/__init__.py
odoo/addons/partner_category_description/models/res_partner_category.py
odoo/addons/partner_category_description/readme/CONTRIBUTORS.md
odoo/addons/partner_category_description/readme/DESCRIPTION.md
odoo/addons/partner_category_description/readme/USAGE.md
odoo/addons/partner_category_description/static/description/icon.png
odoo/addons/partner_category_description/static/description/index.html
odoo/addons/partner_category_description/tests/__init__.py
odoo/addons/partner_category_description/tests/test_partner_category_description.py
odoo/addons/partner_category_description/views/res_partner_category_views.xml
odoo_addon_partner_category_description-17.0.1.0.0.2.dist-info/METADATA
odoo_addon_partner_category_description-17.0.1.0.0.2.dist-info/WHEEL
odoo_addon_partner_category_description-17.0.1.0.0.2.dist-info/top_level.txt
odoo_addon_partner_category_description-17.0.1.0.0.2.dist-info/RECORD
