Metadata-Version: 2.1
Name: odoo-addon-partner_category_description
Version: 17.0.1.0.0.2
Requires-Python: >=3.10
Requires-Dist: odoo>=17.0a,<17.1dev
Summary: Adds a description field to contact categories to improve organization and managment of customer relationships.
Home-page: https://github.com/OCA/partner-contact
License: LGPL-3
Author: Moduon, Odoo Community Association (OCA)
Author-email: support@odoo-community.org
Classifier: Programming Language :: Python
Classifier: Framework :: Odoo
Classifier: Framework :: Odoo :: 17.0
Classifier: License :: OSI Approved :: GNU Lesser General Public License v3 (LGPLv3)
Classifier: Development Status :: 3 - Alpha
